{
  "resourceType": "StructureDefinition",
  "url": "http://hl7.org/v2/StructureDefinition/MFK_M01-K",
  "id": "MFK_M01-K",
  "meta": {
    "profile": [
      "http://hl7.org/v2/StructureDefinition/MessageStructure-Profile"
    ]
  },
  "version": "0.0.1",
  "status": "active",
  "kind": "logical",
  "abstract": false,
  "baseDefinition": "http://hl7.org/v2/StructureDefinition/MessageStructure",
  "derivation": "specialization",
  "differential": {
    "element": [
      {
        "id": "MFK_M01-K",
        "path": "MFK_M01-K",
        "short": "MFK_M01-K",
        "definition": "MFK_M01-K Message Structure",
        "min": 0,
        "max": "*"
      },
      [
        {
          "id": "MFK_M01-K.1-MSH",
          "path": "MFK_M01-K.1-MSH",
          "min": 0,
          "max": "1",
          "definition": "1",
          "short": "1",
          "type": [
            {
              "code": "http://hl7.org/v2/StructureDefinition/MSH"
            }
          ],
          "extension": [
            {
              "url": "http://hl7.org/fhir/StructureDefinition/v2-segment-status",
              "valueCode": "A"
            }
          ]
        }
      ],
      [
        {
          "id": "MFK_M01-K.2-SFT",
          "path": "MFK_M01-K.2-SFT",
          "min": 1,
          "max": "*",
          "definition": "*",
          "short": "*",
          "type": [
            {
              "code": "http://hl7.org/v2/StructureDefinition/SFT"
            }
          ],
          "extension": [
            {
              "url": "http://hl7.org/fhir/StructureDefinition/v2-segment-status",
              "valueCode": "A"
            }
          ]
        }
      ],
      [
        {
          "id": "MFK_M01-K.3-UAC",
          "path": "MFK_M01-K.3-UAC",
          "min": 1,
          "max": "1",
          "definition": "1",
          "short": "1",
          "type": [
            {
              "code": "http://hl7.org/v2/StructureDefinition/UAC"
            }
          ],
          "extension": [
            {
              "url": "http://hl7.org/fhir/StructureDefinition/v2-segment-status",
              "valueCode": "A"
            }
          ]
        }
      ],
      [
        {
          "id": "MFK_M01-K.4-MSA",
          "path": "MFK_M01-K.4-MSA",
          "min": 0,
          "max": "1",
          "definition": "1",
          "short": "1",
          "type": [
            {
              "code": "http://hl7.org/v2/StructureDefinition/MSA"
            }
          ],
          "extension": [
            {
              "url": "http://hl7.org/fhir/StructureDefinition/v2-segment-status",
              "valueCode": "A"
            }
          ]
        }
      ],
      [
        {
          "id": "MFK_M01-K.5-ERR",
          "path": "MFK_M01-K.5-ERR",
          "min": 1,
          "max": "*",
          "definition": "*",
          "short": "*",
          "type": [
            {
              "code": "http://hl7.org/v2/StructureDefinition/ERR"
            }
          ],
          "extension": [
            {
              "url": "http://hl7.org/fhir/StructureDefinition/v2-segment-status",
              "valueCode": "A"
            }
          ]
        }
      ],
      [
        {
          "id": "MFK_M01-K.6-MFI",
          "path": "MFK_M01-K.6-MFI",
          "min": 0,
          "max": "1",
          "definition": "1",
          "short": "1",
          "type": [
            {
              "code": "http://hl7.org/v2/StructureDefinition/MFI"
            }
          ],
          "extension": [
            {
              "url": "http://hl7.org/fhir/StructureDefinition/v2-segment-status",
              "valueCode": "A"
            }
          ]
        }
      ],
      [
        {
          "id": "MFK_M01-K.7-MFA",
          "path": "MFK_M01-K.7-MFA",
          "min": 1,
          "max": "*",
          "definition": "*",
          "short": "*",
          "type": [
            {
              "code": "http://hl7.org/v2/StructureDefinition/MFA"
            }
          ],
          "extension": [
            {
              "url": "http://hl7.org/fhir/StructureDefinition/v2-segment-status",
              "valueCode": "A"
            }
          ]
        }
      ]
    ]
  },
  "title": "HL7 v2 MFK_M01-K Segment Definition",
  "name": "MFK_M01-K",
  "type": "MFK_M01-K",
  "date": "2024-07-24T19:13:18Z"
}
