{
  "resourceType": "StructureDefinition",
  "url": "http://hl7.org/v2/StructureDefinition/M11",
  "id": "M11",
  "meta": {
    "profile": [
      "http://hl7.org/v2/StructureDefinition/Event-Profile"
    ]
  },
  "version": "0.0.1",
  "status": "active",
  "kind": "logical",
  "abstract": false,
  "baseDefinition": "http://hl7.org/v2/StructureDefinition/Event",
  "derivation": "specialization",
  "differential": {
    "element": [
      {
        "id": "M11",
        "path": "M11",
        "short": "M11",
        "definition": "Event M11: Master File Notification - Test/Calculated Observations",
        "min": 0,
        "max": "*"
      }
    ]
  },
  "title": "HL7 v2 M11 Message Definition",
  "name": "M11",
  "type": "M11",
  "date": "2024-07-24T19:13:28Z"
}
